ensemble_gnn/__init__.py
ensemble_gnn/core.py
ensemble_gnn/ensemble.py
ensemble_gnn/utils.py
ensemble_gnn-1.0.3.dist-info/LICENSE
ensemble_gnn-1.0.3.dist-info/METADATA
ensemble_gnn-1.0.3.dist-info/WHEEL
ensemble_gnn-1.0.3.dist-info/top_level.txt
ensemble_gnn-1.0.3.dist-info/RECORD
