Metadata-Version: 2.1
Name: ensemble-gnn
Version: 1.0.3
Summary: Ensemble learning with graph neural networks
Home-page: https://github.com/pievos101/Ensemble-GNN
Author: Bastian Pfeifer
Author-email: bastian.pfeifer@medunigraz.at
License: MIT
Keywords: graph neural networks,ensemble learning
Platform: UNKNOWN
Classifier: Development Status :: 1 - Planning
Classifier: Intended Audience :: Science/Research
Classifier: Intended Audience :: Developers
Classifier: License :: OSI Approved :: MIT License
Classifier: Programming Language :: Python
Classifier: Programming Language :: Python :: 3
Classifier: Programming Language :: Python :: 3.6
Classifier: Programming Language :: Python :: 3.7
Classifier: Programming Language :: Python :: 3.8
Classifier: Programming Language :: Python :: 3.9
Classifier: Programming Language :: Python :: 3.10
Classifier: Programming Language :: Python :: 3 :: Only
Classifier: Topic :: Software Development
Classifier: Topic :: Scientific/Engineering
Classifier: Operating System :: Microsoft :: Windows
Classifier: Operating System :: POSIX :: Linux
Classifier: Operating System :: MacOS
Requires-Python: >=3.6
License-File: LICENSE
Requires-Dist: numpy (>1.0.0)
Requires-Dist: pandas (>0.20.0)
Requires-Dist: scikit-learn (>1.1.0)
Requires-Dist: scipy (>1.5.4)
